{
  "name": "${project.name}",
  "version": "${project.version}",
  "description": "${project.description}",
  "platform": "base",
  "dependencies": [
    {
      "name": "app-platform-minimal",
      "version": "^2.1.0-SNAPSHOT"
    },
    {
      "name": "app-search",
      "version": "^1.0.0-SNAPSHOT"
    }
  ],
  "modules": [
    {
      "name": "mod-graphql",
      "version": "latest"
    },
    {
      "name": "mod-quick-marc",
      "version": "latest"
    },
    {
      "name": "mod-inventory-storage",
      "version": "latest"
    },
    {
      "name": "mod-circulation-storage",
      "version": "latest"
    },
    {
      "name": "mod-inventory",
      "version": "latest"
    },
    {
      "name": "mod-circulation",
      "version": "latest"
    },
    {
      "name": "mod-feesfines",
      "version": "latest"
    },
    {
      "name": "mod-patron-blocks",
      "version": "latest"
    },
    {
      "name": "mod-entities-links",
      "version": "latest"
    },
    {
      "name": "mod-source-record-manager",
      "version": "latest"
    },
    {
      "name": "mod-di-converter-storage",
      "version": "latest"
    },
    {
      "name": "mod-patron",
      "version": "latest"
    },
    {
      "name": "mod-data-export-spring",
      "version": "latest"
    },
    {
      "name": "mod-data-export-worker",
      "version": "latest"
    },
    {
      "name": "mod-remote-storage",
      "version": "latest"
    },
    {
      "name": "mod-calendar",
      "version": "latest"
    },
    {
      "name": "mod-audit",
      "version": "latest"
    },
    {
      "name": "mod-courses",
      "version": "latest"
    },
    {
      "name": "mod-source-record-storage",
      "version": "latest"
    },
    {
      "name": "mod-data-import",
      "version": "latest"
    },
    {
      "name": "mod-email",
      "version": "latest"
    },
    {
      "name": "mod-event-config",
      "version": "latest"
    },
    {
      "name": "mod-notify",
      "version": "latest"
    },
    {
      "name": "mod-sender",
      "version": "latest"
    },
    {
      "name": "mod-template-engine",
      "version": "latest"
    },
    {
      "name": "mod-pubsub",
      "version": "latest"
    },
    {
      "name": "mod-copycat",
      "version": "latest"
    },
    {
      "name": "mod-ncip",
      "version": "latest"
    },
    {
      "name": "mod-inventory-update",
      "version": "latest"
    },
    {
      "name": "mod-user-import",
      "version": "latest"
    },
    {
      "name": "mod-batch-print",
      "version": "latest"
    },
    {
      "name": "mod-record-specifications",
      "version": "latest"
    }
  ],
  "uiModules": [
    {
      "name": "folio_marc-authorities",
      "version": "latest"
    },
    {
      "name": "folio_stripes-authority-components",
      "version": "latest"
    },
    {
      "name": "folio_quick-marc",
      "version": "latest"
    },
    {
      "name": "folio_inventory",
      "version": "latest"
    },
    {
      "name": "folio_servicepoints",
      "version": "latest"
    },
    {
      "name": "folio_plugin-create-inventory-records",
      "version": "latest"
    },
    {
      "name": "folio_plugin-find-instance",
      "version": "latest"
    },
    {
      "name": "folio_checkin",
      "version": "latest"
    },
    {
      "name": "folio_checkout",
      "version": "latest"
    },
    {
      "name": "folio_circulation",
      "version": "latest"
    },
    {
      "name": "folio_plugin-find-user",
      "version": "latest"
    },
    {
      "name": "folio_export-manager",
      "version": "latest"
    },
    {
      "name": "folio_plugin-bursar-export",
      "version": "latest"
    },
    {
      "name": "folio_remote-storage",
      "version": "latest"
    },
    {
      "name": "folio_circulation-log",
      "version": "latest"
    },
    {
      "name": "folio_calendar",
      "version": "latest"
    },
    {
      "name": "folio_courses",
      "version": "latest"
    },
    {
      "name": "folio_requests",
      "version": "latest"
    },
    {
      "name": "folio_data-import",
      "version": "latest"
    },
    {
      "name": "folio_plugin-find-import-profile",
      "version": "latest"
    },
    {
      "name": "folio_tenant-settings",
      "version": "latest"
    },
    {
      "name": "folio_handler-stripes-registry",
      "version": "latest"
    },
    {
      "name": "folio_myprofile",
      "version": "latest"
    },
    {
      "name": "folio_plugin-find-authority",
      "version": "latest"
    },
    {
      "name": "folio_users",
      "version": "latest"
    },
    {
      "name": "folio_stripes-marc-components",
      "version": "latest"
    },
    {
      "name": "folio_stripes-inventory-components",
      "version": "latest"
    }
  ]
}
